{
  "version": 3,
  "requesterUsername": "averyyuwu",
  "requesterAvatarIconUri": {
    "$mid": 1,
    "path": "/u/209247362",
    "scheme": "https",
    "authority": "avatars.githubusercontent.com",
    "query": "v=4"
  },
  "responderUsername": "GitHub Copilot",
  "responderAvatarIconUri": {
    "id": "copilot"
  },
  "initialLocation": "panel",
  "requests": [],
  "sessionId": "d0dd49ff-cf27-4470-a8a4-725aeb7cf21f",
  "creationDate": 1754077590498,
  "isImported": false,
  "lastMessageDate": 1754077590498
}